Workbook

Sheet 1. Assumptions
A1: Tab 1 — ASSUMPTIONS / Giả định đầu vào
A2: Luật chơi: chỉ điền vào các ô MÀU VÀNG. Các ô khác là công thức và sẽ tự tính.
A3: Chỉ số / Item | B3: Optimistic | C3: Base | D3: Pessimistic | E3: Đơn vị | F3: Ghi chú / Note
A4: 1. Product & Pricing / Sản phẩm & Giá
A5: ARPU — Giá bán bình quân/brand/tháng | B5: 3500000 | C5: 2500000 | D5: 1500000 | E5: VND | F5: Base = gói Standard ~2.5tr/tháng. Brand 10–100 chi nhánh; benchmark SaaS SME VN
A6: Adoption rate — % SAM chuyển thành brand trả tiền/tháng | B6: 0.008 | C6: 0.004 | D6: 0.001 | E6: %/tháng | F6: SAM ~3,000–5,000 brands tại HN+HCM; conversion từ pilot ~30%
A7: Total addressable market — SAM (số brand tiềm năng) | B7: 4000 | C7: 4000 | D7: 4000 | E7: brands | F7: Chuỗi F&B 10–100 chi nhánh, đã dùng Zalo OA, có đội CSKH
A8: 2. COGS / Chi phí biến đổi trên mỗi brand/tháng
A9: API cost / brand / tháng (Claude Haiku + Sonnet) | B9: 80000 | C9: 120000 | D9: 180000 | E9: VND | F9: ~50K–200K messages/brand/tháng × Claude Haiku cost; Sonnet cho edge cases
A10: Hidden costs (QA, prompt engineering, model monitoring) | B10: 20000 | C10: 40000 | D10: 70000 | E10: VND | F10: Đừng quên! Cục giết startup AI — labeling, retraining, QA conversation
A11: Infrastructure (server, DB, Zalo OA webhook) / brand | B11: 15000 | C11: 25000 | D11: 40000 | E11: VND | F11: Allocate cloud cost (Railway/AWS) per brand theo volume tin nhắn
A12: Customer success (onboarding support, pro-rata) / brand | B12: 30000 | C12: 50000 | D12: 80000 | E12: VND | F12: Nhân viên CS support onboarding 15 phút + tuần đầu theo dõi
A13: → Tổng COGS / brand / tháng | B13: =SUM(B9:B12) -> 145000 | C13: =SUM(C9:C12) -> 235000 | D13: =SUM(D9:D12) -> 370000
A14: 3. Customer Behavior / Hành vi brand khách hàng
A15: Monthly Churn Rate — % brand rời mỗi tháng | B15: 0.03 | C15: 0.06 | D15: 0.1 | E15: % | F15: B2B SaaS benchmark < 5%/tháng. F&B SME VN có thể cao hơn do ngân sách nhạy cảm
A16: → Số tháng ở lại trung bình = 1/Churn | B16: =IF(B15=0,"-",1/B15) -> 33.333333 | C16: =IF(C15=0,"-",1/C15) -> 16.666667 | D16: =IF(D15=0,"-",1/D15) -> 10
A17: 4. Sales & Marketing / Chi phí thu hút brand
A18: CAC — Chi phí có 1 brand mới (Marketing + Sales) | B18: 1500000 | C18: 3000000 | D18: 6000000 | E18: VND | F18: F&B community event + direct sales. Base = ~1 tháng lương BDR/số brands ký
A19: 5. Fixed Costs / Chi phí cố định hàng tháng
A20: Lương team: 1 PM + 1 Backend Dev + 1 AI Engineer | B20: 80000000 | C20: 100000000 | D20: 130000000 | E20: VND/tháng | F20: Base = ~33tr/người. Scale up nếu cần CS thêm sau M6
A21: Zalo OA partner fee + tools (n8n, monitoring, DB) | B21: 10000000 | C21: 15000000 | D21: 20000000 | E21: VND/tháng | F21: Zalo OA API partner license + stack tool vận hành
A22: Marketing & community (F&B event, content, ads) | B22: 30000000 | C22: 50000000 | D22: 80000000 | E22: VND/tháng | F22: Focus F&B Vietnam community, hội thảo KiotViet/MISA, LinkedIn Ads
A23: Office & misc (co-working, legal, accounting) | B23: 5000000 | C23: 10000000 | D23: 15000000 | E23: VND/tháng | F23: Giai đoạn đầu dùng co-working; không cần văn phòng riêng
A24: → Tổng Fixed Cost / tháng | B24: =SUM(B20:B23) -> 125000000 | C24: =SUM(C20:C23) -> 175000000 | D24: =SUM(D20:D23) -> 245000000
A25: 6. Initial Investment / Vốn đầu tư ban đầu
A26: Vốn đầu tư ban đầu (build MVP 6 tuần + setup) | B26: 400000000 | C26: 400000000 | D26: 400000000 | E26: VND | F26: Chi phí 1 lần: lương team build MVP, Zalo OA setup, legal DPA, pilot support
A27: Tiền mặt ban đầu (sau khi đã trừ vốn đầu tư) | B27: 2000000000 | C27: 2000000000 | D27: 2000000000 | E27: VND | F27: Runway tối thiểu 12 tháng fixed cost. Target: pre-seed ~2 tỷ VND
A28: 7. Discount Rate / Tỷ suất chiết khấu (cho NPV)
A29: Annual discount rate (WACC) | B29: 0.2 | C29: 0.2 | D29: 0.2 | E29: %/năm | F29: Kỳ vọng tối thiểu investor cho AI startup rủi ro cao
A30: → Monthly discount rate = (1+WACC)^(1/12)−1 | B30: =(1+B29)^(1/12)-1 -> 0.01530947 | C30: =(1+C29)^(1/12)-1 -> 0.01530947 | D30: =(1+D29)^(1/12)-1 -> 0.01530947
A31: 8. Decision Note / Ghi chú quyết định
A32: ARPU 2.5tr/tháng (Base) dựa trên benchmark SaaS SME Việt Nam: tool phổ biến nhất cho F&B dao động 1–5tr/tháng, chọn 2.5tr vì giải quyết pain point trực tiếp (mất đơn hàng = mất doanh thu) nên WTP cao hơn "nice-to-have" tools. CAC 3tr (Base) = tổng chi phí events + content + BDR chia cho số brands ký mỗi tháng; con số này cần validate sau 3 tháng pilot đầu tiên.

Sheet 2. Unit Economics
A1: Tab 2 — UNIT ECONOMICS / Kinh tế đơn vị
A2: Tự động tính từ Tab 1. Kiểm tra: LTV/CAC > 3 (Base) và CAC Payback < 12 tháng.
A3: Chỉ số | B3: Optimistic | C3: Base | D3: Pessimistic | E3: Đơn vị | F3: Benchmark / Note
A4: Trên mỗi brand / per brand
A5: ARPU / tháng | B5: ='1. Assumptions'!B5 -> 3500000 | C5: ='1. Assumptions'!C5 -> 2500000 | D5: ='1. Assumptions'!D5 -> 1500000 | E5: VND | F5: Liên kết từ Tab Assumptions
A6: COGS / tháng | B6: ='1. Assumptions'!B13 -> 145000 | C6: ='1. Assumptions'!C13 -> 235000 | D6: ='1. Assumptions'!D13 -> 370000 | E6: VND | F6: Tổng chi phí biến đổi / brand
A7: → Gross Profit / tháng | B7: =B5-B6 -> 3355000 | C7: =C5-C6 -> 2265000 | D7: =D5-D6 -> 1130000 | E7: VND | F7: ARPU − COGS
A8: → Gross Margin % | B8: =IF(B5=0,0,B7/B5) -> 0.95857143 | C8: =IF(C5=0,0,C7/C5) -> 0.906 | D8: =IF(D5=0,0,D7/D5) -> 0.75333333 | F8: AI product target 40–60%. Base phải >40% để sustainable
A9: LTV — Customer Lifetime Value
A10: Số tháng ở lại trung bình | B10: ='1. Assumptions'!B16 -> 33.333333 | C10: ='1. Assumptions'!C16 -> 16.666667 | D10: ='1. Assumptions'!D16 -> 10 | E10: tháng | F10: 1 / Churn Rate từ Tab 1
A11: → LTV = Gross Profit × Số tháng ở lại | B11: =B7*B10 -> 1.1183333e+08 | C11: =C7*C10 -> 37750000 | D11: =D7*D10 -> 11300000 | E11: VND | F11: Tổng lợi nhuận gộp một brand mang lại trong vòng đời
A12: CAC — Customer Acquisition Cost
A13: CAC — Chi phí thu hút 1 brand | B13: ='1. Assumptions'!B19 -> 0 | C13: ='1. Assumptions'!C19 -> 0 | D13: ='1. Assumptions'!D19 -> 0 | E13: VND | F13: Liên kết từ Tab 1 — Section 4
A14: Key Ratios / Tỷ lệ then chốt
A15: → LTV / CAC Ratio | B15: =IF(B13=0,0,B11/B13) -> 0 | C15: =IF(C13=0,0,C11/C13) -> 0 | D15: =IF(D13=0,0,D11/D13) -> 0 | F15: 🎯 Target > 3.0x (tiêu chuẩn vàng VC)
A16: → CAC Payback Period (tháng) | B16: =IF(B7=0,0,B13/B7) -> 0 | C16: =IF(C7=0,0,C13/C7) -> 0 | D16: =IF(D7=0,0,D13/D7) -> 0 | E16: tháng | F16: 🎯 Target < 12 tháng (early-stage SaaS)
A17: Verdict / Kết luận Unit Economics
A18: Unit Economics Status | B18: =IF(AND(B15>=3,B16<=12),"✓ HEALTHY","✗ UNHEALTHY") -> ✗ UNHEALTHY | C18: =IF(AND(C15>=3,C16<=12),"✓ HEALTHY","✗ UNHEALTHY") -> ✗ UNHEALTHY | D18: =IF(AND(D15>=3,D16<=12),"✓ HEALTHY","✗ UNHEALTHY") -> ✗ UNHEALTHY

Sheet 3. P&L & ROI
A1: Tab 3 — P&L & ROI / 24 tháng
A2: Chọn scenario tại B3. Toàn bộ P&L tự cập nhật theo scenario đã chọn.
A3: Chọn scenario: | B3: Base | C3: ← Đổi: Optimistic / Base / Pessimistic
A4: Active scenario index: | B4: =IF(B3="Optimistic",1,IF(B3="Pessimistic",3,2)) -> 2
A5: ARPU / brand / tháng | B5: =IF(B3="Optimistic",'1. Assumptions'!B5,IF(B3="Pessimistic",'1. Assumptions'!D5,'1. Assumptions'!C5)) -> 2500000
A6: Adoption rate | B6: =IF(B3="Optimistic",'1. Assumptions'!B6,IF(B3="Pessimistic",'1. Assumptions'!D6,'1. Assumptions'!C6)) -> 0.004
A7: SAM (số brand tiềm năng) | B7: =IF(B3="Optimistic",'1. Assumptions'!B7,IF(B3="Pessimistic",'1. Assumptions'!D7,'1. Assumptions'!C7)) -> 4000
A8: Total COGS / brand | B8: =IF(B3="Optimistic",'1. Assumptions'!B13,IF(B3="Pessimistic",'1. Assumptions'!D13,'1. Assumptions'!C13)) -> 235000
A9: Monthly Churn Rate | B9: =IF(B3="Optimistic",'1. Assumptions'!B15,IF(B3="Pessimistic",'1. Assumptions'!D15,'1. Assumptions'!C15)) -> 0.06
A10: CAC / brand mới | B10: =IF(B3="Optimistic",'1. Assumptions'!B19,IF(B3="Pessimistic",'1. Assumptions'!D19,'1. Assumptions'!C19)) -> 0
A11: Fixed Cost / tháng | B11: =IF(B3="Optimistic",'1. Assumptions'!B24,IF(B3="Pessimistic",'1. Assumptions'!D24,'1. Assumptions'!C24)) -> 175000000
A12: Initial Investment | B12: =IF(B3="Optimistic",'1. Assumptions'!B27,IF(B3="Pessimistic",'1. Assumptions'!D27,'1. Assumptions'!C27)) -> 2000000000
A13: Initial Cash | B13: =IF(B3="Optimistic",'1. Assumptions'!B28,IF(B3="Pessimistic",'1. Assumptions'!D28,'1. Assumptions'!C28)) -> 0
A14: Monthly Discount Rate | B14: =IF(B3="Optimistic",'1. Assumptions'!B30,IF(B3="Pessimistic",'1. Assumptions'!D30,'1. Assumptions'!C30)) -> 0.01530947
A15: P&L Projection — 24 months (VND)
A16: Month | B16: M1 | C16: M2 | D16: M3 | E16: M4 | F16: M5 | G16: M6 | H16: M7 | I16: M8 | J16: M9 | K16: M10 | L16: M11 | M16: M12 | N16: M13 | O16: M14 | P16: M15 | Q16: M16 | R16: M17 | S16: M18 | T16: M19 | U16: M20 | V16: M21 | W16: M22 | X16: M23 | Y16: M24 | Z16: TOTAL
A17: New brands acquired | B17: =$B$7*$B$6 -> 16 | C17: =$B$7*$B$6 -> 16 | D17: =$B$7*$B$6 -> 16 | E17: =$B$7*$B$6 -> 16 | F17: =$B$7*$B$6 -> 16 | G17: =$B$7*$B$6 -> 16 | H17: =$B$7*$B$6 -> 16 | I17: =$B$7*$B$6 -> 16 | ... Y17: =$B$7*$B$6 -> 16 | Z17: =SUM(C17:Y17) -> 368
A18: Active brands (end of month) | B18: =C17 -> 16 | C18: =B18*(1-$B$9)+C17 -> 31.04 | D18: =C18*(1-$B$9)+D17 -> 45.1776 | E18: =D18*(1-$B$9)+E17 -> 58.466944 | F18: =E18*(1-$B$9)+F17 -> 70.958927 | G18: =F18*(1-$B$9)+G17 -> 82.701392 | H18: =G18*(1-$B$9)+H17 -> 93.739308 | I18: =H18*(1-$B$9)+I17 -> 104.11495 | J18: =I18*(1-$B$9)+J17 -> 113.86805 | ... Y18: =X18*(1-$B$9)+Y17 -> 206.26663 | Z18: =Y18 -> 206.26663
A19: Revenue | B19: =B18*$B$5 -> 40000000 | C19: =C18*$B$5 -> 77600000 | D19: =D18*$B$5 -> 112944000 | E19: =E18*$B$5 -> 146167360 | F19: =F18*$B$5 -> 1.7739732e+08 | G19: =G18*$B$5 -> 2.0675348e+08 | H19: =H18*$B$5 -> 2.3434827e+08 | I19: =I18*$B$5 -> 2.6028737e+08 | ... Y19: =Y18*$B$5 -> 5.1566657e+08 | Z19: =SUM(C19:Y19) -> 7.8812237e+09
A20: COGS (variable cost) | B20: =B18*$B$8 -> 3760000 | C20: =C18*$B$8 -> 7294400 | D20: =D18*$B$8 -> 10616736 | E20: =E18*$B$8 -> 13739732 | F20: =F18*$B$8 -> 16675348 | G20: =G18*$B$8 -> 19434827 | H20: =H18*$B$8 -> 22028737 | I20: =I18*$B$8 -> 24467013 | ... Y20: =Y18*$B$8 -> 48472658 | Z20: =SUM(C20:Y20) -> 7.4083503e+08
A21: Gross Profit | B21: =B19-B20 -> 36240000 | C21: =C19-C20 -> 70305600 | D21: =D19-D20 -> 102327264 | E21: =E19-E20 -> 1.3242763e+08 | F21: =F19-F20 -> 1.6072197e+08 | G21: =G19-G20 -> 1.8731865e+08 | H21: =H19-H20 -> 2.1231953e+08 | I21: =I19-I20 -> 2.3582036e+08 | ... Y21: =Y19-Y20 -> 4.6719391e+08 | Z21: =SUM(C21:Y21) -> 7.1403887e+09
A22: Marketing / Acquisition cost | B22: =B17*$B$10 -> 0 | C22: =C17*$B$10 -> 0 | D22: =D17*$B$10 -> 0 | E22: =E17*$B$10 -> 0 | F22: =F17*$B$10 -> 0 | G22: =G17*$B$10 -> 0 | H22: =H17*$B$10 -> 0 | I22: =I17*$B$10 -> 0 | ... Y22: =Y17*$B$10 -> 0 | Z22: =SUM(C22:Y22) -> 0
A23: Fixed cost (salaries + ops) | B23: =$B$11 -> 175000000 | C23: =$B$11 -> 175000000 | D23: =$B$11 -> 175000000 | E23: =$B$11 -> 175000000 | F23: =$B$11 -> 175000000 | G23: =$B$11 -> 175000000 | H23: =$B$11 -> 175000000 | I23: =$B$11 -> 175000000 | ... Y23: =$B$11 -> 175000000 | Z23: =SUM(C23:Y23) -> 4025000000
A24: Operating Profit (EBITDA) | B24: =B21-B22-B23 -> -138760000 | C24: =C21-C22-C23 -> -104694400 | D24: =D21-D22-D23 -> -72672736 | E24: =E21-E22-E23 -> -42572372 | F24: =F21-F22-F23 -> -14278030 | G24: =G21-G22-G23 -> 12318652 | H24: =H21-H22-H23 -> 37319533 | I24: =I21-I22-I23 -> 60820361 | ... Y24: =Y21-Y22-Y23 -> 2.9219391e+08 | Z24: =SUM(C24:Y24) -> 3.1153887e+09
A25: Cash Flow (after investment) | B25: =B24-$B$12 -> -2138760000 | C25: =C24 -> -104694400 | D25: =D24 -> -72672736 | E25: =E24 -> -42572372 | F25: =F24 -> -14278030 | G25: =G24 -> 12318652 | H25: =H24 -> 37319533 | I25: =I24 -> 60820361 | J25: =J24 -> 82911139 | ... Y25: =Y24 -> 2.9219391e+08 | Z25: =SUM(C25:Y25) -> 3.1153887e+09
A26: Cash Position (cumulative) | B26: =$B$13+B25 -> -2138760000 | C26: =B26+C25 -> -2243454400 | D26: =C26+D25 -> -2316127136 | E26: =D26+E25 -> -2.3586995e+09 | F26: =E26+F25 -> -2.3729775e+09 | G26: =F26+G25 -> -2.3606589e+09 | H26: =G26+H25 -> -2.3233394e+09 | I26: =H26+I25 -> -2.262519e+09 | J26: =I26+J25 -> -2.1796079e+09 | ... Y26: =X26+Y25 -> 9.7662872e+08 | Z26: =Y26 -> 9.7662872e+08
A28: ROI Metrics / Chỉ số đánh giá tổng thể dự án
A29: NPV (Net Present Value, triệu VND) | B29: =($B$13-$B$12+NPV($B$14,C25:Y25))/1000000 -> 381.6188 | C29: (target: > 0)
A30: IRR (Annual, annualized from monthly) | B30: =IFERROR((1+IRR(C25:Y25,0.01))^12-1,"N/A") -> 12.104364 | C30: (target: > 20.0%)
A31: Project Payback (tháng đầu tiên cash position > 0) | B31: =IFERROR(MATCH(TRUE(),C26:Y26>0,0),">24") -> >24 | C31: (target: < 24 tháng)
A32: Runway (tháng trước khi cash position = 0) | B32: =IF(MIN(C26:Y26)>0,">= 24",MATCH(TRUE(),C26:Y26<=0,0)-1) -> #VALUE! | C32: (target: >= 12 tháng)
A34: Final Verdict / Có nên làm dự án này?
A35: Project Decision | B35: =IF(AND(B29>0,ISNUMBER(B30),B30>'1. Assumptions'!C29),"✓ GO — NPV+ và IRR > WACC","✗ WAIT — Cần review assumptions") -> ✓ GO — NPV+ và IRR > WACC

Sheet 4. Sensitivity
A1: Tab 4 — SENSITIVITY / Phân tích độ nhạy
A2: Xem LTV/CAC thay đổi thế nào khi ARPU và Churn Rate thay đổi. Ô XANH = healthy (>3x).
A3: LTV/CAC Ratio — ARPU (hàng) × Churn Rate (cột)
A4: ARPU \ Churn → | B4: 3% | C4: 4% | D4: 5% | E4: 6% | F4: 8% | G4: 10% | H4: 12%
A5: 1.0 tr VND | B5: 8.5 | C5: 6.4 | D5: 5.1 | E5: 4.2 | F5: 3.2 | G5: 2.5 | H5: 2.1
A6: 1.5 tr VND | B6: 14.1 | C6: 10.5 | D6: 8.4 | E6: 7 | F6: 5.3 | G6: 4.2 | H6: 3.5
A7: 2.0 tr VND | B7: 19.6 | C7: 14.7 | D7: 11.8 | E7: 9.8 | F7: 7.4 | G7: 5.9 | H7: 4.9
A8: 2.5 tr VND | B8: 25.2 | C8: 18.9 | D8: 15.1 | E8: 12.6 | F8: 9.4 | G8: 7.5 | H8: 6.3
A9: 3.0 tr VND | B9: 30.7 | C9: 23 | D9: 18.4 | E9: 15.4 | F9: 11.5 | G9: 9.2 | H9: 7.7
A10: 3.5 tr VND | B10: 36.3 | C10: 27.2 | D10: 21.8 | E10: 18.1 | F10: 13.6 | G10: 10.9 | H10: 9.1
A11: 4.0 tr VND | B11: 41.8 | C11: 31.4 | D11: 25.1 | E11: 20.9 | F11: 15.7 | G11: 12.6 | H11: 10.5
A13: Chú thích màu: | B13: ≥ 3.0x Healthy | C13: 1.5–3.0x Caution | D13: < 1.5x Danger
A15: Revenue Month 12 (triệu VND) — ARPU × Adoption Rate
A16: ARPU \ Adopt → | B16: 0.1% | C16: 0.2% | D16: 0.3% | E16: 0.4% | F16: 0.6% | G16: 0.8% | H16: 1.2%
A17: 1.0 tr VND | B17: 35 | C17: 70 | D17: 105 | E17: 140 | F17: 210 | G17: 280 | H17: 419
A18: 1.5 tr VND | B18: 52 | C18: 105 | D18: 157 | E18: 210 | F18: 314 | G18: 419 | H18: 629
A19: 2.0 tr VND | B19: 70 | C19: 140 | D19: 210 | E19: 280 | F19: 419 | G19: 559 | H19: 839
A20: 2.5 tr VND | B20: 87 | C20: 175 | D20: 262 | E20: 349 | F20: 524 | G20: 699 | H20: 1048
A21: 3.0 tr VND | B21: 105 | C21: 210 | D21: 314 | E21: 419 | F21: 629 | G21: 839 | H21: 1258
A22: 3.5 tr VND | B22: 122 | C22: 245 | D22: 367 | E22: 489 | F22: 734 | G22: 978 | H22: 1467
A23: 4.0 tr VND | B23: 140 | C23: 280 | D23: 419 | E23: 559 | F23: 839 | G23: 1118 | H23: 1677
A26: Đơn vị: triệu VND. Xanh > 200tr/tháng, Vàng > 80tr, Đỏ < 80tr
